my_reposmith_bootstrap/__init__.py
my_reposmith_bootstrap/cli.py
my_reposmith_bootstrap-0.1.0.dist-info/licenses/LICENSE
my_reposmith_bootstrap-0.1.0.dist-info/METADATA
my_reposmith_bootstrap-0.1.0.dist-info/WHEEL
my_reposmith_bootstrap-0.1.0.dist-info/entry_points.txt
my_reposmith_bootstrap-0.1.0.dist-info/top_level.txt
my_reposmith_bootstrap-0.1.0.dist-info/RECORD
