Metadata-Version: 2.4
Name: my-reposmith-bootstrap
Version: 0.1.0
Summary: Bootstrap installer for reposmith toolchain (core + extensions + cli).
Author: Tamer
License: MIT
Requires-Python: >=3.10
License-File: LICENSE
Dynamic: license-file
